{
  "perguntas": [
      {
          "questao": "Qual desses animais é um mamífero?",
          "respostas": [
              "Tubarão",
              "Peixe",
              "Golfinho",
              "Águia"
          ],
          "resposta_certa": 2
      },
      {
          "questao": "Qual desses animais pertence ao grupo dos répteis?",
          "respostas": [
              "Coelho",
              "Cobra",
              "Sapo",
              "Pinguim"
          ],
          "resposta_certa": 1
      },
      {
          "questao": "Qual animal é conhecido por usar a ecolocalização para se orientar?",
          "respostas": [
              "Tigre",
              "Elefante",
              "Cavalo",
              "Golfinho"
          ],
          "resposta_certa": 3
      },
      {
          "questao": "Qual dos seguintes animais é o maior terrestre?",
          "respostas": [
              "Rinoceronte",
              "Elefante",
              "Girafa",
              "Hipopótamo"
          ],
          "resposta_certa": 1
      },
      {
          "questao": "Qual animal é famoso por sua habilidade de mudar de cor para se camuflar?",
          "respostas": [
              "Camaleão",
              "Tartaruga",
              "Cavalo-marinho",
              "Golfinho"
          ],
          "resposta_certa": 0
      }
  ]
}
